{
  "summary": "### AI 리포트 요약\n\n최근 크롤링된 자료에 따르면, 알콘, 쿠퍼비전, 바슈롬 브랜드에 대한 포스팅이 각각 301, 178, 160건으로, 특히 알콘 브랜드의 프로모션 활동이 두드러집니다. 서울, 부산 지역에서의 활동이 상대적으로 많으나, 대다수 포스트가 미분류로 되어 있어 지역적 특성을 파악하기 어려운 상황입니다. 교육/세미나 관련 포스팅은 29건으로, ASD, MAX 블루라이트, 멀티포컬 등 구체적인 교육 필요성이 나타납니다.\n\n### 추천 행동\n\n1. **멀티포컬 및 블루라이트 필터 교육**: 블루라이트와 멀티포컬에 대한 교육 콘텐츠 강화.\n2. **지역별 맞춤형 프로모션 전략 수립**: 부산과 서울 중심의 프로모션 효과를 고려한 맞춤형 캠페인 기획.\n3. **교육 세미나 활성화**: ASD 및 스마트피팅 관련 교육 세미나를 정기적으로 개최하여 유통망 보강.\n4. **크롤링 데이터 분류 개선**: 미분류 데이터 최소화를 위해 지역별 태그 강화.\n5. **소셜 미디어 활용**: 게시글의 접근성을 높이기 위해 SNS 채널을 통한 정보 확산 전략 마련.",
  "actions": [
    "상위 활동 지역을 기준으로 ASD/MAX/멀티포컬 교육 대상을 우선 추출하세요.",
    "경쟁사 프로모션 게시글이 많은 지역에는 소비자 상담용 차별화 메시지를 배포하세요.",
    "교육/세미나 활동이 많은 브랜드 키워드를 다음 교육 콘텐츠 주제에 반영하세요."
  ],
  "raw": {
    "total_posts": 639,
    "brand_counts": {
      "알콘": 301,
      "쿠퍼": 178,
      "바슈롬": 160
    },
    "region_counts": {
      "미분류": 478,
      "부산": 48,
      "대구": 27,
      "서울": 21,
      "대전": 17,
      "인천": 12,
      "광주": 11,
      "울산": 11,
      "경기": 4,
      "경남": 4
    },
    "type_counts": {
      "프로모션": 418,
      "체험/증정": 152,
      "교육/세미나": 29,
      "신제품": 6,
      "게시글": 34
    },
    "sample_posts": [
      {
        "월": "2026-06",
        "게시일": "2026-06-23",
        "경과일": "0",
        "최근7일": "1",
        "최근30일": "1",
        "최근90일": "1",
        "지역": "미분류",
        "브랜드": "알콘",
        "활동유형": "프로모션",
        "제목": "창원 상남동 룩스토어 안경원/6월 아큐브데이 특템 찬스",
        "요약": "2+1 행사 중 입니다❤️ 아큐브,알콘,인터로조 등 원데이렌즈 재고확인 및 궁금하신점 있으시면 언제든지 톡톡이나 전화주세요^^ 룩스토어 창원대동점 창원시 성산구 원이대로730 대동백화점내...",
        "URL": "https://blog.naver.com/leeprcp/224324680214",
        "출처": "naver_blog_api",
        "검색어": "알콘 렌즈 행사",
        "블로그명": "룩스토어 창원(대동백화점)",
        "알콘": "1",
        "쿠퍼": "0",
        "바슈롬": "0"
      },
      {
        "월": "2026-06",
        "게시일": "2026-06-23",
        "경과일": "0",
        "최근7일": "1",
        "최근30일": "1",
        "최근90일": "1",
        "지역": "미분류",
        "브랜드": "알콘",
        "활동유형": "프로모션",
        "제목": "6월 콘택트렌즈 역대급 할인 가이드 (아큐브, 바슈롬, 알콘...",
        "요약": "CC렌즈 / 바슈롬 레이셀 자연스러우면서도 또렷한 눈빛을 연출해 주는 프리미엄 컬러·서클 렌즈... 콘택트렌즈 할인 행사는 재고 소진 시 조기 마감될 수 있습니다. 자주 쓰시는 도수가 있다면 방문 전...",
        "URL": "https://blog.naver.com/royglasses/224324517333",
        "출처": "naver_blog_api",
        "검색어": "바슈롬 렌즈 행사",
        "블로그명": "로이안경 수원인계점",
        "알콘": "1",
        "쿠퍼": "0",
        "바슈롬": "0"
      },
      {
        "월": "2026-06",
        "게시일": "2026-06-23",
        "경과일": "0",
        "최근7일": "1",
        "최근30일": "1",
        "최근90일": "1",
        "지역": "미분류",
        "브랜드": "알콘",
        "활동유형": "프로모션",
        "제목": "안경렌즈 변색 누진다초점 하고 싶다고 하시네요.",
        "요약": "투명렌즈 #알콘 #아큐브 #바슈롬 #쿠퍼비젼 #도수없는안경 #패션안경 #메가박스건너편안경 #보호안경... 원플원#행사안경 저희 블로그 글을 읽고 저와 다른 생각을 가지신 분은 댓글 남겨주세요.손에 많은...",
        "URL": "https://blog.naver.com/2696089/224323399118",
        "출처": "naver_blog_api",
        "검색어": "바슈롬 렌즈 행사",
        "블로그명": "안경메신저(OK안경공장)",
        "알콘": "1",
        "쿠퍼": "0",
        "바슈롬": "0"
      },
      {
        "월": "2026-06",
        "게시일": "2026-06-22",
        "경과일": "1",
        "최근7일": "1",
        "최근30일": "1",
        "최근90일": "1",
        "지역": "미분류",
        "브랜드": "알콘",
        "활동유형": "프로모션",
        "제목": "용원안경점 합리적인 가격으로 제공하는 으뜸아이안경",
        "요약": "아니라 렌즈 품질과 시력 검사까지 함께 고려해야 합니다. 이번 행사에서는 국내 브랜드 안경테와... 또한 아큐브, 바슈롬, 알콘, 쿠퍼비전 등 인기 콘택트렌즈 브랜드 제품도 합리적인 가격으로 구매할 수...",
        "URL": "https://blog.naver.com/tldnjs731/224323807090",
        "출처": "naver_blog_api",
        "검색어": "바슈롬 렌즈 행사",
        "블로그명": "소소한 일상, 꾸준한 성장",
        "알콘": "1",
        "쿠퍼": "0",
        "바슈롬": "0"
      },
      {
        "월": "2026-06",
        "게시일": "2026-06-22",
        "경과일": "1",
        "최근7일": "1",
        "최근30일": "1",
        "최근90일": "1",
        "지역": "미분류",
        "브랜드": "알콘",
        "활동유형": "체험/증정",
        "제목": "[금천구렌즈, 독산동렌즈]알콘 원데이 렌즈 90+30 프로모션...",
        "요약": "알콘 원데이 90+30 프로모션 안내 기간: 6월 1일 ~ 소진 시 종료 (한정 수량!) 내용: 행사 대상 제품 대용량(90P) 구매 시 ➡️ 소용량(30P) 정품 1팩 추가 증정! 대상 제품: 워터렌즈 근시 / 프리시전원 근시...",
        "URL": "https://blog.naver.com/davichgeumcheon/224323722908",
        "출처": "naver_blog_api",
        "검색어": "알콘 렌즈 행사",
        "블로그명": "[다비치안경 금천점]",
        "알콘": "1",
        "쿠퍼": "0",
        "바슈롬": "0"
      },
      {
        "월": "2026-06",
        "게시일": "2026-06-22",
        "경과일": "1",
        "최근7일": "1",
        "최근30일": "1",
        "최근90일": "1",
        "지역": "미분류",
        "브랜드": "알콘",
        "활동유형": "프로모션",
        "제목": "청주 안경 으뜸플러스안경 성안길점 2층 제대로 가성비",
        "요약": "드라이브맥스 렌즈 추천해드릴게요. 콘택트렌즈도 지금 행사 품목으로 바슈롬 소프렌 원데이, 알콘... 착색렌즈, 변색렌즈 모두 더 할인 들어가는중이라 이렇게 이벤트 할 때 맞춰오시길 바라요. 2층인 만큼...",
        "URL": "https://blog.naver.com/eeeooot/224323667124",
        "출처": "naver_blog_api",
        "검색어": "바슈롬 콘택트렌즈 이벤트",
        "블로그명": "해서민 블로그",
        "알콘": "1",
        "쿠퍼": "0",
        "바슈롬": "0"
      },
      {
        "월": "2026-06",
        "게시일": "2026-06-22",
        "경과일": "1",
        "최근7일": "1",
        "최근30일": "1",
        "최근90일": "1",
        "지역": "미분류",
        "브랜드": "알콘",
        "활동유형": "체험/증정",
        "제목": "알콘 원데이 포트폴리오 90+30 행사",
        "요약": "알콘 근시 대용량 구매시 30개 추가증정!!! 워터렌즈 근시 대용량(90) 구매시 30개 추가증정 프리시전 근시 대용량(90) 구매시 30개 추가증정 매장앞 주차가능, 제로페이,백화점상품권가능, 고유가...",
        "URL": "https://blog.naver.com/wooil011/224323664807",
        "출처": "naver_blog_api",
        "검색어": "알콘 렌즈 행사",
        "블로그명": "다비치안경 먹골역점",
        "알콘": "1",
        "쿠퍼": "0",
        "바슈롬": "0"
      },
      {
        "월": "2026-06",
        "게시일": "2026-06-22",
        "경과일": "1",
        "최근7일": "1",
        "최근30일": "1",
        "최근90일": "1",
        "지역": "미분류",
        "브랜드": "알콘",
        "활동유형": "체험/증정",
        "제목": "대치콘택트] 알콘 렌즈... 토탈원·프리시전원·토탈30 행사...",
        "요약": "이번 알콘 행사에서는 추가 렌즈 증정 혜택으로 평소보다 더욱 경제적으로 구매하실 수 있으니 렌즈 구매를 계획하고 계셨다면 꼭 활용해 보세요. 알콘 렌즈 행사 상담 및 구매는 다비치안경...",
        "URL": "https://blog.naver.com/mh8470mh/224323612211",
        "출처": "naver_blog_api",
        "검색어": "알콘 렌즈 행사",
        "블로그명": "다비치안경보청기 대치점",
        "알콘": "1",
        "쿠퍼": "0",
        "바슈롬": "0"
      },
      {
        "월": "2026-06",
        "게시일": "2026-06-22",
        "경과일": "1",
        "최근7일": "1",
        "최근30일": "1",
        "최근90일": "1",
        "지역": "미분류",
        "브랜드": "알콘",
        "활동유형": "프로모션",
        "제목": "[부영이의 선명한 이야기 EP.01]",
        "요약": "안경행사, #이벤트, #상암콘택트렌즈, #콘텍트렌즈, #콘텍트세일, #스포츠고글, #수색역안경... 알콘렌즈, #아큐브렌즈, #오아시스렌즈, #마이데이렌즈, #쿠퍼비전, #바슈롬, #오유파인 #마포안경 #마포구안경...",
        "URL": "https://blog.naver.com/top50sa/224323520694",
        "출처": "naver_blog_api",
        "검색어": "바슈롬 콘택트렌즈 이벤트",
        "블로그명": "가성비안경원❤️으뜸50안경 상암DMC점",
        "알콘": "1",
        "쿠퍼": "0",
        "바슈롬": "0"
      },
      {
        "월": "2026-06",
        "게시일": "2026-06-22",
        "경과일": "1",
        "최근7일": "1",
        "최근30일": "1",
        "최근90일": "1",
        "지역": "부산",
        "브랜드": "알콘",
        "활동유형": "프로모션",
        "제목": "[ 서면렌즈 ] \"NEW\" 보석의 반짝임을 담은 로젬므 출시 !!...",
        "요약": "및 행사상품제외 ) #다비치 #다비치안경 #다비치서면 #서면안경점 #부산렌즈가게 #다비치렌즈... 다비치알콘렌즈 #고유가지원금 #김하온 #고유가지원금사용가능처 #고유가사용처 #고유가지원금안경점...",
        "URL": "https://blog.naver.com/davichseomyeon/224323514110",
        "출처": "naver_blog_api",
        "검색어": "알콘 렌즈 행사",
        "블로그명": "다비치안경 부산 서면점",
        "알콘": "1",
        "쿠퍼": "0",
        "바슈롬": "0"
      }
    ]
  }
}